{
  "canisters": {
    "minimal_dapp": {
      "main": "src/minimal_dapp/main.mo",
      "type": "motoko"
    },
    "minimal_dapp_assets": {
      "dependencies": [
        "minimal_dapp"
      ],
      "frontend": {
        "entrypoint": "src/minimal_dapp_assets/src/index.html"
      },
      "source": [
        "src/minimal_dapp_assets/assets",
        "dist/minimal_dapp_assets/"
      ],
      "type": "assets"
    }
  },
  "defaults": {
    "build": {
      "args": "",
      "packtool": ""
    }
  },
  "version": 1
}